CHANGES.txt
LICENSE.txt
MANIFEST.in
README.txt
setup.py
Cirrus.egg-info/PKG-INFO
Cirrus.egg-info/SOURCES.txt
Cirrus.egg-info/dependency_links.txt
Cirrus.egg-info/requires.txt
Cirrus.egg-info/top_level.txt
bin/dns_setup.py
bin/update_host.py
cirrus/__init__.py
cirrus/r53.py
contrib/dns_update
contrib/update_host_sample_IAM_policy.txt
examples/dns_example.yaml