Metadata-Version: 1.0
Name: Cirrus
Version: 0.9
Summary: A set of tools for configuring Amazon route53
Home-page: https://launchpad.net/cirrus
Author: Tim Kuhlman
Author-email: tim@backgroundprocess.com
License: BSD
Keywords: cloud boto route53
Platform: UNKNOWN
Classifier: Development Status :: 4 - Beta
Classifier: Topic :: Utilities
Classifier: License :: OSI Approved :: BSD License
